standardjson/__init__.py
standardjson/encoder_funcs.py
standardjson/encoders.py
standardjson-0.3.0.dist-info/DESCRIPTION.rst
standardjson-0.3.0.dist-info/METADATA
standardjson-0.3.0.dist-info/metadata.json
standardjson-0.3.0.dist-info/RECORD
standardjson-0.3.0.dist-info/top_level.txt
standardjson-0.3.0.dist-info/WHEEL
