Metadata-Version: 2.0
Name: standardjson
Version: 0.3.0
Summary: JSON encoder that aims to be fully compliant with specifications ECMA-262 and ECMA-404.
Home-page: https://github.com/audreyr/json262
Author: Audrey Roy
Author-email: audreyr@gmail.com
License: BSD
Keywords: standardjson
Platform: UNKNOWN
Classifier: Development Status :: 3 - Alpha
Classifier: Intended Audience :: Developers
Classifier: License :: OSI Approved :: BSD License
Classifier: Natural Language :: English
Classifier: Programming Language :: Python :: 2
Classifier: Programming Language :: Python :: 2.6
Classifier: Programming Language :: Python :: 2.7
Classifier: Programming Language :: Python :: 3
Classifier: Programming Language :: Python :: 3.3
